<annotation>
	<folder>disss2</folder>
	<filename>p440.jpg</filename>
	<path>C:\disss2\p440.jpg</path>
	<source>
		<database>Unknown</database>
	</source>
	<size>
		<width>392</width>
		<height>427</height>
		<depth>3</depth>
	</size>
	<segmented>0</segmented>
	<object>
		<name>tube</name>
		<pose>Unspecified</pose>
		<truncated>0</truncated>
		<difficult>0</difficult>
		<bndbox>
			<xmin>133</xmin>
			<ymin>189</ymin>
			<xmax>204</xmax>
			<ymax>213</ymax>
		</bndbox>
	</object>
	<object>
		<name>tube</name>
		<pose>Unspecified</pose>
		<truncated>0</truncated>
		<difficult>0</difficult>
		<bndbox>
			<xmin>207</xmin>
			<ymin>207</ymin>
			<xmax>282</xmax>
			<ymax>231</ymax>
		</bndbox>
	</object>
</annotation>
