<annotation>
	<folder>train</folder>
	<filename>p111.jpg</filename>
	<path>C:\Users\Lenovo\models-master\research\object_detection\images\train\p111.jpg</path>
	<source>
		<database>Unknown</database>
	</source>
	<size>
		<width>425</width>
		<height>231</height>
		<depth>3</depth>
	</size>
	<segmented>0</segmented>
	<object>
		<name>tube</name>
		<pose>Unspecified</pose>
		<truncated>0</truncated>
		<difficult>0</difficult>
		<bndbox>
			<xmin>26</xmin>
			<ymin>64</ymin>
			<xmax>228</xmax>
			<ymax>98</ymax>
		</bndbox>
	</object>
	<object>
		<name>scattered_barrel</name>
		<pose>Unspecified</pose>
		<truncated>0</truncated>
		<difficult>0</difficult>
		<bndbox>
			<xmin>269</xmin>
			<ymin>69</ymin>
			<xmax>338</xmax>
			<ymax>106</ymax>
		</bndbox>
	</object>
</annotation>
